stackdiac/__init__.py
stackdiac/api/__init__.py
stackdiac/api/server.py
stackdiac/cli/__init__.py
stackdiac/cli/build.py
stackdiac/cli/create.py
stackdiac/cli/ui.py
stackdiac/models/__init__.py
stackdiac/models/backend.py
stackdiac/models/binary.py
stackdiac/models/cluster.py
stackdiac/models/config.py
stackdiac/models/operation.py
stackdiac/models/provider.py
stackdiac/models/repo.py
stackdiac/models/secret.py
stackdiac/models/spec.py
stackdiac/models/stack.py
stackdiac/stackd/__init__.py
stackdiac/stackd/filters.py
stackdiac/stackd/sdmod.py
stackdiac/stackd/stackd.py
stackdiac/ui/4753c5ba57962b4d7bf8.woff
stackdiac/ui/6d63d0501e5ed7b79dab.woff2
stackdiac/ui/bundle.js
stackdiac/ui/bundle.js.LICENSE.txt
stackdiac/ui/index.html
stackdiac/views/__init__.py
stackdiac/views/module.py
stackdiac-0.0.1.dev31.dist-info/LICENSE
stackdiac-0.0.1.dev31.dist-info/METADATA
stackdiac-0.0.1.dev31.dist-info/WHEEL
stackdiac-0.0.1.dev31.dist-info/entry_points.txt
stackdiac-0.0.1.dev31.dist-info/RECORD
