Metadata-Version: 2.1
Name: stackdiac
Version: 0.0.1.dev31
Summary: 
License: MIT
Author: sysr9
Author-email: 38893296+sysr9@users.noreply.github.com
Requires-Python: >=3.10,<4.0
Classifier: License :: OSI Approved :: MIT License
Classifier: Programming Language :: Python :: 3
Classifier: Programming Language :: Python :: 3.10
Classifier: Programming Language :: Python :: 3.11
Requires-Dist: click (>=8.1.3,<9.0.0)
Requires-Dist: coloredlogs (>=15.0.1,<16.0.0)
Requires-Dist: deepmerge (>=1.1.0,<2.0.0)
Requires-Dist: fastapi (>=0.95.0,<0.96.0)
Requires-Dist: gitpython (>=3.1.31,<4.0.0)
Requires-Dist: hvac (>=1.1.0,<2.0.0)
Requires-Dist: jinja2 (>=3.1.2,<4.0.0)
Requires-Dist: mergedeep (>=1.3.4,<2.0.0)
Requires-Dist: pydantic (>=1.10.6,<2.0.0)
Requires-Dist: pyyaml (>=6.0,<7.0)
Requires-Dist: pyyaml-include (>=1.3,<2.0)
Requires-Dist: requests (>=2.28.2,<3.0.0)
Requires-Dist: uvicorn (>=0.21.1,<0.22.0)
